libzet/Attributes.py
libzet/NoCompare.py
libzet/Zettel.py
libzet/__init__.py
libzet/editing.py
libzet/parsing.py
libzet/util/edit.py
libzet-2.2.5.dist-info/LICENSE
libzet-2.2.5.dist-info/METADATA
libzet-2.2.5.dist-info/WHEEL
libzet-2.2.5.dist-info/top_level.txt
libzet-2.2.5.dist-info/RECORD
