Metadata-Version: 2.1
Name: libzet
Version: 2.2.5
Summary: Python3 library for zettel reading.
Author-email: OneRedDime <onereddime@protonmail.com>
License: GPLv2
Project-URL: Homepage, https://github.com/OneRedDime/libzet
Requires-Python: <4,>=3.7
License-File: LICENSE
Requires-Dist: icalendar
Requires-Dist: pyyaml
Requires-Dist: superdate
